spot2mp3/__init__.py
spot2mp3/cli.py
spot2mp3/data/__init__.py
spot2mp3/data/oauth.json
spot2mp3/data/spotify_creds.json
spot2mp3-1.0.3.dist-info/LICENSE
spot2mp3-1.0.3.dist-info/METADATA
spot2mp3-1.0.3.dist-info/WHEEL
spot2mp3-1.0.3.dist-info/entry_points.txt
spot2mp3-1.0.3.dist-info/top_level.txt
spot2mp3-1.0.3.dist-info/RECORD
