Metadata-Version: 2.1
Name: spot2mp3
Version: 1.0.3
Summary: A CLI tool to download Spotify playlist/album tracks as mp3 files.
Home-page: https://github.com/gooosexe/spot2mp3
Author: Oliver Huang
Author-email: ohuang4131@gmail.com
License: GPLv3
Classifier: Programming Language :: Python :: 3
Classifier: License :: OSI Approved :: GNU General Public License v3 (GPLv3)
Classifier: Operating System :: OS Independent
Requires-Python: >=3.8
License-File: LICENSE
